Metadata-Version: 1.1
Name: nose-pyannotate
Version: 0.2.0
Summary: Pyannotate plugin for nose
Home-page: https://github.com/xiaket/nose-pyannotate
Author: Kai Xia
Author-email: xiaket@gmail.com
License: UNKNOWN
Keywords: nose,nosetest,pyannotate
Platform: UNKNOWN
Classifier: Development Status :: 4 - Beta
Classifier: License :: OSI Approved :: MIT License
Classifier: Topic :: Software Development :: Testing :: Unit
